MANIFEST.in
setup.py
djangorestframework_amauth.egg-info/PKG-INFO
djangorestframework_amauth.egg-info/SOURCES.txt
djangorestframework_amauth.egg-info/dependency_links.txt
djangorestframework_amauth.egg-info/requires.txt
djangorestframework_amauth.egg-info/top_level.txt
rest_framework_am_auth/__init__.py
rest_framework_am_auth/account_manager_client.py
rest_framework_am_auth/authentication.py
rest_framework_am_auth/permissions.py
rest_framework_am_auth/settings.py
rest_framework_am_auth/token_info.py
rest_framework_am_auth/management/__init__.py
rest_framework_am_auth/management/commands/__init__.py
rest_framework_am_auth/management/commands/sync_perms_with_am.py