Metadata-Version: 1.0
Name: djangorestframework-amauth
Version: 1.4
Summary: AccountManager auth backend for DRF.
Home-page: UNKNOWN
Author: GS Labs
Author-email: UNKNOWN
License: UNKNOWN
Platform: UNKNOWN
